{
    "type": "force",
    "categories": [
        {
            "name": "行业战疫", 
            "keyword": {},
            "base": "行业战疫"
        },
        {
            "name": "境内疫情", 
            "keyword": {},
            "base": "境内疫情"
        },
        {
            "name": "境外疫情", 
            "keyword": {},
            "base": "境外疫情"
        },
        {
            "name": "政府行动", 
            "keyword": {},
            "base": "政府行动"
        },
        {
            "name": "辟谣", 
            "keyword": {},
            "base": "辟谣"
        },
        {
            "name": "事实", 
            "keyword": {},
            "base": "事实"
        },
        {
            "name": "误区", 
            "keyword": {},
            "base": "误区"
        },
        {
            "name": "谣言", 
            "keyword": {},
            "base": "谣言"
        }
    ],
    "nodes": [ 
        {
            "name": "父节点", 
            "symbolSize": 3,
            "category": 0 
        },
        {
            "name": "二级父节点1",
            "symbolSize": 8,
            "category": 1
        },
        {
            "name": "二级父节点2",
            "symbolSize": 10,
            "category": 2
        },
        {
            "name": "子节点1",
            "symbolSize": 10,
            "category": 3
        },
        {
            "name": "子节点2",
            "symbolSize": 15,
            "category": 4
        },
        {
            "name": "子节点3",
            "symbolSize": 9,
            "category": 5
        },
        {
            "name": "子节点4",
            "symbolSize": 11,
            "category": 6
        },
        {
            "name": "子节点5",
            "symbolSize": 11,
            "category": 7
        }
    ],
    "links": [ 
        {
            "source": 0, 
            "target": 1 
        },
        {
            "source": 0,
            "target": 2
        },
        {
            "source": 1,
            "target": 3
        },
        {
            "source": 1,
            "target": 4
        },
        {
            "source": 2,
            "target": 5
        },
        {
            "source": 2,
            "target": 6
        },
        {
            "source": 4,
            "target": 7
        }
    ]
}